testref/__init__.py
testref/pandoc_filter.py
testref/parse_pytest_xunit2.py
testref/resources/check.png
testref/resources/check_128x128.png
testref/resources/check_16x16.png
testref/resources/check_32x32.png
testref/resources/check_64x64.png
testref/resources/cross.png
testref/resources/cross_128x128.png
testref/resources/cross_16x16.png
testref/resources/cross_32x32.png
testref/resources/cross_64x64.png
testref-0.1.dist-info/METADATA
testref-0.1.dist-info/WHEEL
testref-0.1.dist-info/entry_points.txt
testref-0.1.dist-info/top_level.txt
testref-0.1.dist-info/RECORD
