Metadata-Version: 2.1
Name: testref
Version: 0.1
Summary: Tools for embedding references to test-cases in your documentation.
Home-page: https://github.com/speezepearson/testref
Author: speezepearson
Author-email: speeze.pearson+1097@gmail.com
License: UNKNOWN
Keywords: test documentation
Platform: UNKNOWN
Classifier: Development Status :: 3 - Alpha
Classifier: Intended Audience :: Developers
Classifier: Topic :: Software Development :: Documentation
Classifier: Programming Language :: Python :: 3.7
Provides-Extra: dev
Provides-Extra: test
